razo/__init__.py
razo/__main__.py
razo/razo_langpack_d.py
razo_langpack/__init__.py
razo_langpack/how_to_turn_language.py
razo-20230.220.dist-info/LICENSE
razo-20230.220.dist-info/METADATA
razo-20230.220.dist-info/WHEEL
razo-20230.220.dist-info/top_level.txt
razo-20230.220.dist-info/RECORD
