Metadata-Version: 2.1
Name: razo
Version: 20230.220
Summary: Run a system in Python,can connect to the main system
Home-page: https://github.com/fredongit/razo
Author: Fred Dumb
Author-email: vmuonline@126.com
Maintainer: The Razo Community
License: MIT
Platform: UNKNOWN
Classifier: Development Status :: 5 - Production/Stable
Classifier: Programming Language :: Python :: 3
Classifier: Intended Audience :: End Users/Desktop
Classifier: Programming Language :: Python
Classifier: Programming Language :: Python :: 3.8
Classifier: Programming Language :: Python :: 3.9
Classifier: Programming Language :: Python :: 3.10
Classifier: Programming Language :: Python :: 3 :: Only
Classifier: License :: OSI Approved :: MIT License
Classifier: Topic :: Utilities
Requires-Python: >=3.8
License-File: LICENSE
Requires-Dist: numpy
Requires-Dist: password
